{"title":"Desktop GIRLS nude SlideShow-Fastlanevision","uid":6011116,"size":13639605,"categoryP":"other","categoryS":"pictures","magnet":"?xt=urn:btih:0bcbd057186a7b1f9df885435d9147132c6b3099&amp;dn=Desktop+GIRLS+nude+SlideShow-Fastlanevision&amp;tr=udp%3A%2F%2Ftracker.openbittorrent.com%3A80&amp;tr=udp%3A%2F%2Fopen.demonii.com%3A1337&amp;tr=udp%3A%2F%2Ftracker.coppersurfer.tk%3A6969&amp;tr=udp%3A%2F%2Fexodus.desync.com%3A6969","seeders":0,"leechers":1,"uploader":"TPB_","files":278,"time":1291460268,"description":"533x400, optimal for Windows sidebar Slideshow.... :)\n\n","torrent":{"xt":"urn:btih:0bcbd057186a7b1f9df885435d9147132c6b3099","amp;dn":"Desktop+GIRLS+nude+SlideShow-Fastlanevision","amp;tr":["udp%3A%2F%2Ftracker.openbittorrent.com%3A80","udp%3A%2F%2Fopen.demonii.com%3A1337","udp%3A%2F%2Ftracker.coppersurfer.tk%3A6969","udp%3A%2F%2Fexodus.desync.com%3A6969"],"infoHash":"0bcbd057186a7b1f9df885435d9147132c6b3099","infoHashBuffer":{"type":"Buffer","data":[11,203,208,87,24,106,123,31,157,248,133,67,93,145,71,19,44,107,48,153]},"announce":[],"urlList":[]}}