{"title":"Megamind.SCR.XViD-xSCR","uid":6086462,"size":741329998,"categoryP":"video","categoryS":"movies","magnet":"?xt=urn:btih:105f79224c29e919d45082b65815ae829b142fdc&amp;dn=Megamind.SCR.XViD-xSCR&amp;tr=udp%3A%2F%2Ftracker.openbittorrent.com%3A80&amp;tr=udp%3A%2F%2Fopen.demonii.com%3A1337&amp;tr=udp%3A%2F%2Ftracker.coppersurfer.tk%3A6969&amp;tr=udp%3A%2F%2Fexodus.desync.com%3A6969","seeders":0,"leechers":1,"uploader":"TvTeam","files":5,"time":1294351092,"description":". \n  &lt;a href=&quot;\nhttp://www.torrentday.com/&quot; rel=&quot;nofollow&quot; target=&quot;_NEW&quot;&gt;\nhttp://www.torrentday.com/&lt;/a&gt;        :     The Hottest Private Tracker On The Net!!! &lt;a href=&quot;\nhttp://www.torrentday.com&quot; rel=&quot;nofollow&quot; target=&quot;_NEW&quot;&gt;\nhttp://www.torrentday.com&lt;/a&gt;          :     Once you visit it, You can't stop yourself visiting Torrentday everyday ;)\n\n\n               www . TorrentDay . Com \n\n(((((((((((((= Enjoy No RAR releases =))))))))))))))))))))\n\n\n...................................NFO:....................................\n\n.Megamind (2010\n &lt;a href=&quot;\nhttp://www.imdb.com/title/tt1001526/&quot; rel=&quot;nofollow&quot; target=&quot;_NEW&quot;&gt;\nhttp://www.imdb.com/title/tt1001526/&lt;/a&gt;\n\n592 x 400 900kbts\nMP3 VBR 128kbps\n\n@x","torrent":{"xt":"urn:btih:105f79224c29e919d45082b65815ae829b142fdc","amp;dn":"Megamind.SCR.XViD-xSCR","amp;tr":["udp%3A%2F%2Ftracker.openbittorrent.com%3A80","udp%3A%2F%2Fopen.demonii.com%3A1337","udp%3A%2F%2Ftracker.coppersurfer.tk%3A6969","udp%3A%2F%2Fexodus.desync.com%3A6969"],"infoHash":"105f79224c29e919d45082b65815ae829b142fdc","infoHashBuffer":{"type":"Buffer","data":[16,95,121,34,76,41,233,25,212,80,130,182,88,21,174,130,155,20,47,220]},"announce":[],"urlList":[]}}