{"title":"WikiLeaks_(Entire_Site)_12_3_2010","uid":6012822,"size":14406371,"categoryP":"other","categoryS":"other","magnet":"?xt=urn:btih:22e13ce730d011ddeec571f02f6dec23482089f6&amp;dn=WikiLeaks_%28Entire_Site%29_12_3_2010&amp;tr=udp%3A%2F%2Ftracker.openbittorrent.com%3A80&amp;tr=udp%3A%2F%2Fopen.demonii.com%3A1337&amp;tr=udp%3A%2F%2Ftracker.coppersurfer.tk%3A6969&amp;tr=udp%3A%2F%2Fexodus.desync.com%3A6969","seeders":0,"leechers":1,"uploader":"LoStXxTrAgIcXx","files":2,"time":1291524240,"description":"WikiLeaks_(Entire_Site)_12_3_2010","torrent":{"xt":"urn:btih:22e13ce730d011ddeec571f02f6dec23482089f6","amp;dn":"WikiLeaks_%28Entire_Site%29_12_3_2010","amp;tr":["udp%3A%2F%2Ftracker.openbittorrent.com%3A80","udp%3A%2F%2Fopen.demonii.com%3A1337","udp%3A%2F%2Ftracker.coppersurfer.tk%3A6969","udp%3A%2F%2Fexodus.desync.com%3A6969"],"infoHash":"22e13ce730d011ddeec571f02f6dec23482089f6","infoHashBuffer":{"type":"Buffer","data":[34,225,60,231,48,208,17,221,238,197,113,240,47,109,236,35,72,32,137,246]},"announce":[],"urlList":[]}}