{"title":"Hells_Kitchen_US_S08E15_Season_Finale_XviD.avi","uid":6047559,"size":367240265,"categoryP":"video","categoryS":"tv_shows","magnet":"?xt=urn:btih:25d05124bf4cf50161235e8ab8bae2aeeed3b0dc&amp;dn=Hells_Kitchen_US_S08E15_Season_Finale_XviD.avi&amp;tr=udp%3A%2F%2Ftracker.openbittorrent.com%3A80&amp;tr=udp%3A%2F%2Fopen.demonii.com%3A1337&amp;tr=udp%3A%2F%2Ftracker.coppersurfer.tk%3A6969&amp;tr=udp%3A%2F%2Fexodus.desync.com%3A6969","seeders":0,"leechers":0,"uploader":"eugene_barns","files":1,"time":1292613073,"description":"Hells Kitchen US - S08E15 - Season Finale\n\n","torrent":{"xt":"urn:btih:25d05124bf4cf50161235e8ab8bae2aeeed3b0dc","amp;dn":"Hells_Kitchen_US_S08E15_Season_Finale_XviD.avi","amp;tr":["udp%3A%2F%2Ftracker.openbittorrent.com%3A80","udp%3A%2F%2Fopen.demonii.com%3A1337","udp%3A%2F%2Ftracker.coppersurfer.tk%3A6969","udp%3A%2F%2Fexodus.desync.com%3A6969"],"infoHash":"25d05124bf4cf50161235e8ab8bae2aeeed3b0dc","infoHashBuffer":{"type":"Buffer","data":[37,208,81,36,191,76,245,1,97,35,94,138,184,186,226,174,238,211,176,220]},"announce":[],"urlList":[]}}