{"title":"VA - MOS Clubbers Guide 2009 German Edition [2009]","uid":6025823,"size":232368338,"categoryP":"audio","categoryS":"music","magnet":"?xt=urn:btih:2995acaaaffdaeb49d2e736e643e0e6f0d81d29b&amp;dn=VA+-+MOS+Clubbers+Guide+2009+German+Edition+%5B2009%5D&amp;tr=udp%3A%2F%2Ftracker.openbittorrent.com%3A80&amp;tr=udp%3A%2F%2Fopen.demonii.com%3A1337&amp;tr=udp%3A%2F%2Ftracker.coppersurfer.tk%3A6969&amp;tr=udp%3A%2F%2Fexodus.desync.com%3A6969","seeders":0,"leechers":1,"uploader":"rezar1337","files":8,"time":1291927853,"description":"\n\n\n  Artist...:   VA\n  Title....:   MOS Clubbers Guide 2009__Germa\n\n  Label....:   Ministry Of Sound Germany\n  Genre....:   House\n  Quality..:   VBR kbit/ 44,1 kHz\n  Source...:   CDDA\n  Ripdate..:   Jan-30-2009\n  Encoder..:   LAME 3.97 (VBR -V2 --vbr-new)\n  Tracks...:   02\n\n  Tracklist:\n\n  Cd1\n\n  01.Va - Clubbers Guide 2009 CD1     77:58\n\n  Laurent Wolf - No stress (Gold &amp; Ortega Remix)\n  Kid Cudi - Day 'n' nite (Mobin Masters Remix)\n  Real Booty Babes - I kissed a girl (PH Electro Remix)\n  Michael Mind - Baker street (Vocal Club Mix)\n  Klaas - Make you feel (Klaas Stomp Vocal Mix)\n  G&amp;G - Personal Jesus (TV Rock Mix)\n  Jean Elan - Where's your head at (Klaas Remix)\n  Dahbruck and Klein - Open up your arms (Joachim Garraud Remix)\n  Davis Anjay - Finally (Club Mix)\n  Ian Carey - Lose control\n  Ida Corr - Ride my tempo (Oliver Lamg Dojo Mix)\n  2 Tyme - Missing you (Jason Herd's Mix)\n  Tonka - Orca (Ian Pooley's Orca Mallorca Remix)\n  Avantgarde - Get down (Again in 2008)\n  DJ Antoine - December\n  Corenell - Welcome to the weekend (Club Mix)\n  VooDoo &amp; Serano - Sunglasses at night (Club Mix)\n  Thomas Gold - Losing my religion\n  Resource - Hymn (VooDoo &amp; Serano Remix)\n  CJ Stone - Shining star (Chris Ortega Remix)\n\n  Cd2\n\n  01.Va - Clubbers Guide 2009 CD2     77:45\n\n  Thomas Gold - Everybody be somebody (Hy2RoGeN &amp; Nikola Mix)\n  Luetzenkirchen - All that jazz (Popof Remix 01)\n  R.O.N.Y. - I feel love\n  Micha Moore - I like that (Patric La Funk Remix)\n  Rudenko - Everybody (Dabruck &amp; Klein Remix)\n  Abel Ramos - Rotterdam city of love (Axwell Re-Edit)\n  namTRAK - This is what u need (Tocadisco Remix)\n  Tomcraft - When I was sixteen\n  Marco Denmark - I can't fight this (Albin Myers &amp; Jonas Sellberg Remix)\n  Plastic Funk - Show me what you got (Phunk Investigation Remix)\n  Duke Jansen - Staring at the sun (DBN Remix)\n  Luomo - Tessio (Stimming Remix)\n  Clavin Harris - Merrymaking at my place (Deadmau5 Remix)\n  D.O.N.S. - You used to hold me (TV Rock Remix)\n  Dahlbaeck and Diaz - Can't slow down (Morphine) (Jean Elan Remix)\n  Micha Moore - Close your eyes (Club Mix)\n  City Sneakerz - Want 2 be (Smax &amp; Gold Mix)\n  Markus Gardeweg - Fairplay (Let there be love) (D.O.N.S. &amp; DBN Remix)\n  Clubworxx - Put your hands up in the air (Main Mix)\n  Morjac - When we're together (Plastik Funk Remix)\n\n\n                                      221,6 MB\n  Notes:\n\n\n\n\n\n\n\n\n","torrent":{"xt":"urn:btih:2995acaaaffdaeb49d2e736e643e0e6f0d81d29b","amp;dn":"VA+-+MOS+Clubbers+Guide+2009+German+Edition+%5B2009%5D","amp;tr":["udp%3A%2F%2Ftracker.openbittorrent.com%3A80","udp%3A%2F%2Fopen.demonii.com%3A1337","udp%3A%2F%2Ftracker.coppersurfer.tk%3A6969","udp%3A%2F%2Fexodus.desync.com%3A6969"],"infoHash":"2995acaaaffdaeb49d2e736e643e0e6f0d81d29b","infoHashBuffer":{"type":"Buffer","data":[41,149,172,170,175,253,174,180,157,46,115,110,100,62,14,111,13,129,210,155]},"announce":[],"urlList":[]}}