{"title":"The.Ring.Pack[320p.quark]","uid":6030314,"size":1108949838,"categoryP":"video","categoryS":"movies","magnet":"?xt=urn:btih:36af4226c67c73825f9bda24b11663c9834835b6&amp;dn=The.Ring.Pack%5B320p.quark%5D&amp;tr=udp%3A%2F%2Ftracker.openbittorrent.com%3A80&amp;tr=udp%3A%2F%2Fopen.demonii.com%3A1337&amp;tr=udp%3A%2F%2Ftracker.coppersurfer.tk%3A6969&amp;tr=udp%3A%2F%2Fexodus.desync.com%3A6969","seeders":0,"leechers":0,"uploader":"twentyforty","files":4,"time":1292067635,"description":"Click on &quot;Files&quot; tab (lower part of uTorrent program-window) - right-click \non file you don't need - choose &quot;Don't download&quot;. \n(uTorrent would show &quot;Skipped&quot;).\nOther torrent-programs offer very similar step.\n\n*** 2-pass encoding for PC, PS3 or Xbox . ***\n*** Video is H264; audio is AAC LC and container is MP4. ***\n\n&quot;Home&quot; of my torrents (for Bookmark/Favorites in your browser)  &lt;a href=&quot;\nhttp://thepiratebay.se/user/twentyforty&quot; rel=&quot;nofollow&quot; target=&quot;_NEW&quot;&gt;\nhttp://thepiratebay.se/user/twentyforty&lt;/a&gt;\n\nREQUESTS ARE &quot;FROZEN&quot;.\n\n*******************************************************************\n\nRingu.1998.H264[320p.quark].mp4\n\nRating: 7.4/10 - from 20,924 users\nDirected by Hideo Nakata. \nStarring Yuko Takeuchi, Nanako Matsushima, Miki Nakatani. \nA mysterious video kills whomever views it, unless that viewer can solve its mystery. &lt;a href=&quot;\nhttp://www.imdb.com/title/tt0178868/&quot; rel=&quot;nofollow&quot; target=&quot;_NEW&quot;&gt;\nhttp://www.imdb.com/title/tt0178868/&lt;/a&gt;\nSubtitles: external, English\n\nThe.Ring.2002.BDrip.H264[320p.quark].mp4\n\nRating: 7.2/10 - from 85,822 users\nDirected by Gore Verbinski. \nStarring Naomi Watts, Martin Henderson, David Dorfman. \nA young journalist must investigate a mysterious videotape which seems to cause the death of anyone in a week of viewing it. &lt;a href=&quot;\nhttp://www.imdb.com/title/tt0298130/&quot; rel=&quot;nofollow&quot; target=&quot;_NEW&quot;&gt;\nhttp://www.imdb.com/title/tt0298130/&lt;/a&gt;\n\nThe.Ring.Two.2005.UNRATeD.H264[320p.quark].mp4\n\nRating: 5.1/10 - from 29,086 users\nDirected by Hideo Nakata. \nStarring Naomi Watts, Simon Baker, David Dorfman. \nSix months after the incidents involving the lethal videotape, new clues prove that there is a new evil lurking in the darkness. &lt;a href=&quot;\nhttp://www.imdb.com/title/tt0377109/&quot; rel=&quot;nofollow&quot; target=&quot;_NEW&quot;&gt;\nhttp://www.imdb.com/title/tt0377109/&lt;/a&gt;\n\n","torrent":{"xt":"urn:btih:36af4226c67c73825f9bda24b11663c9834835b6","amp;dn":"The.Ring.Pack%5B320p.quark%5D","amp;tr":["udp%3A%2F%2Ftracker.openbittorrent.com%3A80","udp%3A%2F%2Fopen.demonii.com%3A1337","udp%3A%2F%2Ftracker.coppersurfer.tk%3A6969","udp%3A%2F%2Fexodus.desync.com%3A6969"],"infoHash":"36af4226c67c73825f9bda24b11663c9834835b6","infoHashBuffer":{"type":"Buffer","data":[54,175,66,38,198,124,115,130,95,155,218,36,177,22,99,201,131,72,53,182]},"announce":[],"urlList":[]}}