{"title":"[ / Brazzers.com] Diana Prince","uid":6041937,"size":230332401,"categoryP":"porn","categoryS":"movies","magnet":"?xt=urn:btih:3786f591b7c4dd651978c1089094826a8de49d02&amp;dn=%5B+%2F+Brazzers.com%5D+Diana+Prince&amp;tr=udp%3A%2F%2Ftracker.openbittorrent.com%3A80&amp;tr=udp%3A%2F%2Fopen.demonii.com%3A1337&amp;tr=udp%3A%2F%2Ftracker.coppersurfer.tk%3A6969&amp;tr=udp%3A%2F%2Fexodus.desync.com%3A6969","seeders":0,"leechers":1,"uploader":"exmnova","files":1,"time":1292411666,"description":"/ Brazzers.com] Diana Prince\n &lt;a href=&quot;\nhttp://www.picswan.com/adult/share-B1B5_4D08964B.html&quot; rel=&quot;nofollow&quot; target=&quot;_NEW&quot;&gt;\nhttp://www.picswan.com/adult/share-B1B5_4D08964B.html&lt;/a&gt;\n &lt;a href=&quot;\nhttp://www.picswan.com/adult/share-07E3_4D08964B.html&quot; rel=&quot;nofollow&quot; target=&quot;_NEW&quot;&gt;\nhttp://www.picswan.com/adult/share-07E3_4D08964B.html&lt;/a&gt;","torrent":{"xt":"urn:btih:3786f591b7c4dd651978c1089094826a8de49d02","amp;dn":"%5B+%2F+Brazzers.com%5D+Diana+Prince","amp;tr":["udp%3A%2F%2Ftracker.openbittorrent.com%3A80","udp%3A%2F%2Fopen.demonii.com%3A1337","udp%3A%2F%2Ftracker.coppersurfer.tk%3A6969","udp%3A%2F%2Fexodus.desync.com%3A6969"],"infoHash":"3786f591b7c4dd651978c1089094826a8de49d02","infoHashBuffer":{"type":"Buffer","data":[55,134,245,145,183,196,221,101,25,120,193,8,144,148,130,106,141,228,157,2]},"announce":[],"urlList":[]}}