{"title":"AmKingdom - Coeds Series 3 Franziska","uid":5954892,"size":46633833,"categoryP":"porn","categoryS":"pictures","magnet":"?xt=urn:btih:52e252fea82adde85249ab5c5aa9e21d67333d0a&amp;dn=AmKingdom+-+Coeds+Series+3+Franziska&amp;tr=udp%3A%2F%2Ftracker.openbittorrent.com%3A80&amp;tr=udp%3A%2F%2Fopen.demonii.com%3A1337&amp;tr=udp%3A%2F%2Ftracker.coppersurfer.tk%3A6969&amp;tr=udp%3A%2F%2Fexodus.desync.com%3A6969","seeders":0,"leechers":1,"uploader":"Alanies","files":166,"time":1289676689,"description":"Preview:\n &lt;a href=&quot;\nhttp://postimg.com/image/25000/24001.jpg&quot; rel=&quot;nofollow&quot; target=&quot;_NEW&quot;&gt;\nhttp://postimg.com/image/25000/24001.jpg&lt;/a&gt;","torrent":{"xt":"urn:btih:52e252fea82adde85249ab5c5aa9e21d67333d0a","amp;dn":"AmKingdom+-+Coeds+Series+3+Franziska","amp;tr":["udp%3A%2F%2Ftracker.openbittorrent.com%3A80","udp%3A%2F%2Fopen.demonii.com%3A1337","udp%3A%2F%2Ftracker.coppersurfer.tk%3A6969","udp%3A%2F%2Fexodus.desync.com%3A6969"],"infoHash":"52e252fea82adde85249ab5c5aa9e21d67333d0a","infoHashBuffer":{"type":"Buffer","data":[82,226,82,254,168,42,221,232,82,73,171,92,90,169,226,29,103,51,61,10]},"announce":[],"urlList":[]}}