{"title":"TV.Shows.Pack.Jan.16.H264[CHOOSE]","uid":6108735,"size":2527175995,"categoryP":"video","categoryS":"tv_shows","magnet":"?xt=urn:btih:5576221c83485adfead297ab1cf67f0298b4dbe8&amp;dn=TV.Shows.Pack.Jan.16.H264%5BCHOOSE%5D&amp;tr=udp%3A%2F%2Ftracker.openbittorrent.com%3A80&amp;tr=udp%3A%2F%2Fopen.demonii.com%3A1337&amp;tr=udp%3A%2F%2Ftracker.coppersurfer.tk%3A6969&amp;tr=udp%3A%2F%2Fexodus.desync.com%3A6969","seeders":0,"leechers":1,"uploader":"twentyforty","files":10,"time":1295225616,"description":"Click on &quot;Files&quot; tab (lower part of uTorrent program-window) - right-click \non file you don't need - choose &quot;Don't download&quot;. \n(uTorrent would show &quot;Skipped&quot;).\nOther torrent-programs offer very similar step.\n\n*** 2-pass encoding for PC, PS3 or Xbox . ***\n*** Video is H264; audio is AAC LC and container is MP4. ***\n\n&quot;Home&quot; of my torrents (for Bookmark/Favorites in your browser)  &lt;a href=&quot;\nhttp://thepiratebay.se/user/twentyforty&quot; rel=&quot;nofollow&quot; target=&quot;_NEW&quot;&gt;\nhttp://thepiratebay.se/user/twentyforty&lt;/a&gt;\n\nNOTE: TimeToLive 48h (torrent's TTL)\n\n10 Files (2.35 GB) \nName\tSize\nBuffy.The.Vampire.Slayer.S08E01.MOTION.COMIC.mp4\t42.3 MB\nDesperate.Housewives.S07E13.480p.HDTV.H264.mp4\t171.7 MB\nFamily.Guy.S09E10.480p.HDTV.H264.mp4\t87.9 MB\nPulse.S01E01.Pilot.720p.H264.mp4\t499.7 MB\nThe.68th.Annual.Golden.Globe.Awards.2011.H264[352p.quark].mp4\t400.4 MB\nThe.Cape.2011.S01E03.480p.HDTV.H264.mp4\t172.8 MB\nThe.Simpsons.S22E11.480p.HDTV.H264.mp4\t87.9 MB\nYoung.Justice.S01E01.Independence.Day.Part.1.mp4\t122.2 MB\nYoung.Justice.S01E02.Independence.Day.Part.2.Fireworks.mp4\t122.1 MB\n\n+ Sophies.Choice.1982.352p.H264.mp4\t703.1 MB\n\n","torrent":{"xt":"urn:btih:5576221c83485adfead297ab1cf67f0298b4dbe8","amp;dn":"TV.Shows.Pack.Jan.16.H264%5BCHOOSE%5D","amp;tr":["udp%3A%2F%2Ftracker.openbittorrent.com%3A80","udp%3A%2F%2Fopen.demonii.com%3A1337","udp%3A%2F%2Ftracker.coppersurfer.tk%3A6969","udp%3A%2F%2Fexodus.desync.com%3A6969"],"infoHash":"5576221c83485adfead297ab1cf67f0298b4dbe8","infoHashBuffer":{"type":"Buffer","data":[85,118,34,28,131,72,90,223,234,210,151,171,28,246,127,2,152,180,219,232]},"announce":[],"urlList":[]}}