{"title":"Uptown.2009.DVDRip.XviD-VoMiT","uid":5936462,"size":735239042,"categoryP":"video","categoryS":"movies","magnet":"?xt=urn:btih:8ed7e1f668076547e369410a0a821c6921219028&amp;dn=Uptown.2009.DVDRip.XviD-VoMiT&amp;tr=udp%3A%2F%2Ftracker.openbittorrent.com%3A80&amp;tr=udp%3A%2F%2Fopen.demonii.com%3A1337&amp;tr=udp%3A%2F%2Ftracker.coppersurfer.tk%3A6969&amp;tr=udp%3A%2F%2Fexodus.desync.com%3A6969","seeders":0,"leechers":1,"uploader":"TvTeam","files":4,"time":1288984121,"description":". \n  &lt;a href=&quot;\nhttp://www.torrentday.com/&quot; rel=&quot;nofollow&quot; target=&quot;_NEW&quot;&gt;\nhttp://www.torrentday.com/&lt;/a&gt;        :     The Hottest Private Tracker On The Net!!!\n\n\n               www . TorrentDay . Com \n(((((((((((((= Enjoy No RAR releases =))))))))))))))))))))\n\n\n...................................NFO:....................................\n\n.                                                 \n                                            \n                                       \n                                       \n                                      \n                                \n                                       \n                                            \n                                                          \n                                                         \n                                               \n                                \n                                  \n                                        \n                                    \n                                      \n                                              \n                                  \n                                   \n                                     \n                                 \n                        \n                      \n                      \n                 \n                 PROUDLY        \n                  PRESENTS TO YOU          \n                              \n                 \n               \n                        \n                                         \n                Uptown (2009)             \n                                              \n   Video Codec....: XviD-1.2.2               \n    Video Bitrate..: 980 kbps                  \n      Audio Codec....: AC3     Stereo              \n     Audio Bitrate..: 192 kbps                   \n       Aspect Ratio...: 1.81:1                      \n      Resolution.....: 640 x 352                 \n     Frame Rate.....: 23.976 fps                \n     Genre..........: Drama                     \n    Runtime........: 75 mins                   \n    RAR Count......: 50x15                     \n    Audio Language.: English                   \n     Subtitles......: N/A                       \n        DVD Date.......: N/A                        \n       Release Date...: 11.05.2010                  \n        Theater Date...: N/A                       \n        IMDB Rating....: 4.9/10 (8 votes)           \n                                                     \n                                                       \n                       \n                        \n                    \n                     \n                                                                      \n                     &lt;a href=&quot; http://www.imdb.com/title/tt1419989&quot; rel=&quot;nofollow&quot; target=&quot;_NEW&quot;&gt; http://www.imdb.com/title/tt1419989&lt;/a&gt;                 \n                                                                          \n                                                    \n                          \n                             \n                                 \n                                                                          \n           Ben has been single for a long time. For his part, he is       \n           a loner but as well a romantic: he enjoys the solitude of      \n           his simple being but appreciates intelligent and witty         \n           company just the same. By yielding to both extremes, Ben       \n           remains caught between reason and arousal. Isabel has          \n           been married for a year. The passion that had once             \n           carried her 5-year relationship has lost its pulse.            \n           Passive, protective, and without poise, it now threatens       \n           to claim hers. Waiting in abeyance, Isabel is lost             \n           between loyalty and loneliness. Uptown is where they come      \n           together.                                                      \n                                                                          \n                                                    \n                        \n                            \n                                 \n                                                                          \n           Chris Riquinha............. : ........................Ben      \n           Meissa Hampton............. : .....................Isabel      \n           Deirdre Herlihy............ : .......................Beth      \n           Derek M. McAllister........ : ....................Kasheem      \n                                                                          \n                                                                      \n                      \n                             \n                       \n         \n                                                                        \n                                                                            \n                   Thanks to our friends at SADPANDA. Enjoy!                \n                                                                            \n                                                                        \n                       \n                          \n                  \n             \n                                                                        \n              VoMiT is now looking for:                                     \n                                                                            \n               1.50mbit+ EU dump site for release spreading.                \n               2.100mbit+ affil sites for XviD/DVDR.                        \n               3.10mbit+ 100GB dumps for personal group use.                \n               4.US/EU pre DVD suppliers.                                   \n                                                                            \n              If u can help us with any of those, contact us at:            \n                                                                            \n                                &lt;a class=&quot;__cf_email__&quot; href=&quot;/cdn-cgi/l/email-protection&quot; data-cfemail=&quot;51273e3c382511392422397f3038&quot;&gt;[email&amp;#160;protected]&lt;/a&gt;&lt;script cf-hash='f9e31' type=&quot;text/javascript&quot;&gt;\n/* &lt;![CDATA[ */!function(){try{var t=&quot;currentScript&quot;in document?document.currentScript:function(){for(var t=document.getElementsByTagName(&quot;script&quot;),e=t.length;e--;)if(t[e].getAttribute(&quot;cf-hash&quot;))return t[e]}();if(t&amp;&amp;t.previousSibling){var e,r,n,i,c=t.previousSibling,a=c.getAttribute(&quot;data-cfemail&quot;);if(a){for(e=&quot;&quot;,r=parseInt(a.substr(0,2),16),n=2;a.length-n;n+=2)i=parseInt(a.substr(n,2),16)^r,e+=String.fromCharCode(i);e=document.createTextNode(e),c.parentNode.replaceChild(e,c)}}}catch(u){}}();/* ]]&gt; */&lt;/script&gt;                               \n                                                                            \n                              Have a nice day :P                            \n                                                                            \n                        \n                               \n                          \n             \n                                                                        \n                 JFKDVD DiAMOND CME iMBT DPiMP HNRDVD WRD DVDR              \n                                                                            \n                 KART3LDVD HNR DoNE SAPHiRE IGUANA HLS FRAGMENT             \n                                                                            \n                 HAGGiS JUMANJi SADPANDA CLUE FiCO VH-PROD TNAN             \n                                                                            \n                                                          \n  \n   Have you hugged your toilet today? \n   \n   :               :\n   :.&gt; 2003 &lt;..::..&gt;  Ascii unfortunately made by SlowBeat  &lt;..::..&gt;  2010 &lt;.:","torrent":{"xt":"urn:btih:8ed7e1f668076547e369410a0a821c6921219028","amp;dn":"Uptown.2009.DVDRip.XviD-VoMiT","amp;tr":["udp%3A%2F%2Ftracker.openbittorrent.com%3A80","udp%3A%2F%2Fopen.demonii.com%3A1337","udp%3A%2F%2Ftracker.coppersurfer.tk%3A6969","udp%3A%2F%2Fexodus.desync.com%3A6969"],"infoHash":"8ed7e1f668076547e369410a0a821c6921219028","infoHashBuffer":{"type":"Buffer","data":[142,215,225,246,104,7,101,71,227,105,65,10,10,130,28,105,33,33,144,40]},"announce":[],"urlList":[]}}