{"title":"El Pais 23 Enero 2011","uid":6121854,"size":10632446,"categoryP":"other","categoryS":"e_books","magnet":"?xt=urn:btih:93b27a6c0085a3d1bf340552a10bebcd51d39862&amp;dn=El+Pais+23+Enero+2011&amp;tr=udp%3A%2F%2Ftracker.openbittorrent.com%3A80&amp;tr=udp%3A%2F%2Fopen.demonii.com%3A1337&amp;tr=udp%3A%2F%2Ftracker.coppersurfer.tk%3A6969&amp;tr=udp%3A%2F%2Fexodus.desync.com%3A6969","seeders":0,"leechers":1,"uploader":"chusca","files":3,"time":1295742024,"description":"Diario El Pais 23 Enero 2011 ","torrent":{"xt":"urn:btih:93b27a6c0085a3d1bf340552a10bebcd51d39862","amp;dn":"El+Pais+23+Enero+2011","amp;tr":["udp%3A%2F%2Ftracker.openbittorrent.com%3A80","udp%3A%2F%2Fopen.demonii.com%3A1337","udp%3A%2F%2Ftracker.coppersurfer.tk%3A6969","udp%3A%2F%2Fexodus.desync.com%3A6969"],"infoHash":"93b27a6c0085a3d1bf340552a10bebcd51d39862","infoHashBuffer":{"type":"Buffer","data":[147,178,122,108,0,133,163,209,191,52,5,82,161,11,235,205,81,211,152,98]},"announce":[],"urlList":[]}}