{"title":"Saw.IV.UNRATED.DVDRip.XviD-DiAMOND","uid":6094708,"size":743557928,"categoryP":"video","categoryS":"movies","magnet":"?xt=urn:btih:97c652568a5c2c846944a3fbe46cf8df6b935b87&amp;dn=Saw.IV.UNRATED.DVDRip.XviD-DiAMOND&amp;tr=udp%3A%2F%2Ftracker.openbittorrent.com%3A80&amp;tr=udp%3A%2F%2Fopen.demonii.com%3A1337&amp;tr=udp%3A%2F%2Ftracker.coppersurfer.tk%3A6969&amp;tr=udp%3A%2F%2Fexodus.desync.com%3A6969","seeders":0,"leechers":0,"uploader":".BONE.","files":5,"time":1294714753,"description":"Jigsaw and his apprentice Amanda are dead. Now, upon the news of Detective Kerry's murder, two seasoned FBI profilers... See full summary Ã‚Â»","torrent":{"xt":"urn:btih:97c652568a5c2c846944a3fbe46cf8df6b935b87","amp;dn":"Saw.IV.UNRATED.DVDRip.XviD-DiAMOND","amp;tr":["udp%3A%2F%2Ftracker.openbittorrent.com%3A80","udp%3A%2F%2Fopen.demonii.com%3A1337","udp%3A%2F%2Ftracker.coppersurfer.tk%3A6969","udp%3A%2F%2Fexodus.desync.com%3A6969"],"infoHash":"97c652568a5c2c846944a3fbe46cf8df6b935b87","infoHashBuffer":{"type":"Buffer","data":[151,198,82,86,138,92,44,132,105,68,163,251,228,108,248,223,107,147,91,135]},"announce":[],"urlList":[]}}