{"title":"Enter.the.Void.2009.DVDRip.XviD.FINSUB.ONLY ","uid":6049442,"size":2982379520,"categoryP":"video","categoryS":"movies","magnet":"?xt=urn:btih:b72c3a70a9b8e2d09cf75378cfdfe3c97d5cc3ee&amp;dn=Enter.the.Void.2009.DVDRip.XviD.FINSUB.ONLY+&amp;tr=udp%3A%2F%2Ftracker.openbittorrent.com%3A80&amp;tr=udp%3A%2F%2Fopen.demonii.com%3A1337&amp;tr=udp%3A%2F%2Ftracker.coppersurfer.tk%3A6969&amp;tr=udp%3A%2F%2Fexodus.desync.com%3A6969","seeders":0,"leechers":0,"uploader":"FatFreddy420","files":-1,"time":1292671300,"description":"Oscar ja hÃƒÂ¤nen siskonsa Linda ovat juuri muuttaneet Tokioon. Oscar on huumediileri ja Linda strippaa yÃƒÂ¶kerhossa. ErÃƒÂ¤ÃƒÂ¤nÃƒÂ¤ yÃƒÂ¶nÃƒÂ¤ poliisi saa Oscarin kiinni ja ampuu hÃƒÂ¤net kuoliaaksi. HÃƒÂ¤n on aiemmin luvannut siskolleen, ettei koskaan jÃƒÂ¤tÃƒÂ¤ tÃƒÂ¤tÃƒÂ¤ yksin ja niinpÃƒÂ¤ hÃƒÂ¤nen sielunsa kieltÃƒÂ¤ytyy lÃƒÂ¤htemÃƒÂ¤stÃƒÂ¤ elÃƒÂ¤vien luota. Alkaa painajaismainen matka lÃƒÂ¤pi kaupungin. Menneisyys, nykyhetki ja tulevaisuus sulautuvat epÃƒÂ¤todelliseen tajunnanvirtaan.","torrent":{"xt":"urn:btih:b72c3a70a9b8e2d09cf75378cfdfe3c97d5cc3ee","amp;dn":"Enter.the.Void.2009.DVDRip.XviD.FINSUB.ONLY+","amp;tr":["udp%3A%2F%2Ftracker.openbittorrent.com%3A80","udp%3A%2F%2Fopen.demonii.com%3A1337","udp%3A%2F%2Ftracker.coppersurfer.tk%3A6969","udp%3A%2F%2Fexodus.desync.com%3A6969"],"infoHash":"b72c3a70a9b8e2d09cf75378cfdfe3c97d5cc3ee","infoHashBuffer":{"type":"Buffer","data":[183,44,58,112,169,184,226,208,156,247,83,120,207,223,227,201,125,92,195,238]},"announce":[],"urlList":[]}}