{"title":"Aathmakatha (2010) Malayalam DVDRip Xvid AC3 5.1 ESub@Mastitorre","uid":6100048,"size":1562443511,"categoryP":"video","categoryS":"movies","magnet":"?xt=urn:btih:c1967e5d28e2ea071ac477c1b6b1a7061d8de674&amp;dn=Aathmakatha+%282010%29+Malayalam+DVDRip+Xvid+AC3+5.1+ESub%40Mastitorre&amp;tr=udp%3A%2F%2Ftracker.openbittorrent.com%3A80&amp;tr=udp%3A%2F%2Fopen.demonii.com%3A1337&amp;tr=udp%3A%2F%2Ftracker.coppersurfer.tk%3A6969&amp;tr=udp%3A%2F%2Fexodus.desync.com%3A6969","seeders":0,"leechers":1,"uploader":"amanrulz","files":4,"time":1294929510,"description":"mastitorrents.com\n &lt;a href=&quot;\nhttp://mastitorrents.com/forums/index.php&quot; rel=&quot;nofollow&quot; target=&quot;_NEW&quot;&gt;\nhttp://mastitorrents.com/forums/index.php&lt;/a&gt;\n\nInfo\n &lt;a href=&quot;\nhttp://img253.imageshack.us/img253/6153/aathmakathanfo.jpg&quot; rel=&quot;nofollow&quot; target=&quot;_NEW&quot;&gt;\nhttp://img253.imageshack.us/img253/6153/aathmakathanfo.jpg&lt;/a&gt;","torrent":{"xt":"urn:btih:c1967e5d28e2ea071ac477c1b6b1a7061d8de674","amp;dn":"Aathmakatha+%282010%29+Malayalam+DVDRip+Xvid+AC3+5.1+ESub%40Mastitorre","amp;tr":["udp%3A%2F%2Ftracker.openbittorrent.com%3A80","udp%3A%2F%2Fopen.demonii.com%3A1337","udp%3A%2F%2Ftracker.coppersurfer.tk%3A6969","udp%3A%2F%2Fexodus.desync.com%3A6969"],"infoHash":"c1967e5d28e2ea071ac477c1b6b1a7061d8de674","infoHashBuffer":{"type":"Buffer","data":[193,150,126,93,40,226,234,7,26,196,119,193,182,177,167,6,29,141,230,116]},"announce":[],"urlList":[]}}