{"title":"UFC.Tribute.To.The.Troops.2.DSR.XviD-XWT","uid":6121580,"size":1261833026,"categoryP":"video","categoryS":"tv_shows","magnet":"?xt=urn:btih:c57b063e6e00f27e88b03a67e2825b710623782e&amp;dn=UFC.Tribute.To.The.Troops.2.DSR.XviD-XWT&amp;tr=udp%3A%2F%2Ftracker.openbittorrent.com%3A80&amp;tr=udp%3A%2F%2Fopen.demonii.com%3A1337&amp;tr=udp%3A%2F%2Ftracker.coppersurfer.tk%3A6969&amp;tr=udp%3A%2F%2Fexodus.desync.com%3A6969","seeders":0,"leechers":1,"uploader":"SAFCukO09","files":4,"time":1295774239,"description":"[center]Filename      : UFC.Tribute.To.The.Troops.2.DSR.XviD-XWT.avi\nAir Date      : January 22nd 2011\nGenre         : MMA\nChannel       : ESPN\nAspect Ratio  : 16:9 (640x368)\nContainer     : AVI\nVideo Codec   : XviD\nAudio Codec   : MPEG-1 Audio Layer III  (128kbs)\nVideo Bitrate : 1050kbps\nSource        : DSR\nPlay Time     : 2 Hours 24 Mins\nRelease Size  : 1.17 GiG\n[/center]","torrent":{"xt":"urn:btih:c57b063e6e00f27e88b03a67e2825b710623782e","amp;dn":"UFC.Tribute.To.The.Troops.2.DSR.XviD-XWT","amp;tr":["udp%3A%2F%2Ftracker.openbittorrent.com%3A80","udp%3A%2F%2Fopen.demonii.com%3A1337","udp%3A%2F%2Ftracker.coppersurfer.tk%3A6969","udp%3A%2F%2Fexodus.desync.com%3A6969"],"infoHash":"c57b063e6e00f27e88b03a67e2825b710623782e","infoHashBuffer":{"type":"Buffer","data":[197,123,6,62,110,0,242,126,136,176,58,103,226,130,91,113,6,35,120,46]},"announce":[],"urlList":[]}}