{"title":"Spartiacus the complete Series[Season 1][Hard English subs]","uid":6087128,"size":4601596242,"categoryP":"video","categoryS":"tv_shows","magnet":"?xt=urn:btih:d6b77429f5bdbb44e889f89c2ab50fd5a7b7acc9&amp;dn=Spartiacus+the+complete+Series%5BSeason+1%5D%5BHard+English+subs%5D&amp;tr=udp%3A%2F%2Ftracker.openbittorrent.com%3A80&amp;tr=udp%3A%2F%2Fopen.demonii.com%3A1337&amp;tr=udp%3A%2F%2Ftracker.coppersurfer.tk%3A6969&amp;tr=udp%3A%2F%2Fexodus.desync.com%3A6969","seeders":0,"leechers":1,"uploader":"frosty4322","files":13,"time":1294380125,"description":"Complete 13 Series of Spartacus, Blood and Sand with Hard English Subs by SnowStorm","torrent":{"xt":"urn:btih:d6b77429f5bdbb44e889f89c2ab50fd5a7b7acc9","amp;dn":"Spartiacus+the+complete+Series%5BSeason+1%5D%5BHard+English+subs%5D","amp;tr":["udp%3A%2F%2Ftracker.openbittorrent.com%3A80","udp%3A%2F%2Fopen.demonii.com%3A1337","udp%3A%2F%2Ftracker.coppersurfer.tk%3A6969","udp%3A%2F%2Fexodus.desync.com%3A6969"],"infoHash":"d6b77429f5bdbb44e889f89c2ab50fd5a7b7acc9","infoHashBuffer":{"type":"Buffer","data":[214,183,116,41,245,189,187,68,232,137,248,156,42,181,15,213,167,183,172,201]},"announce":[],"urlList":[]}}