{"title":"Belle e Trapanate","uid":5969801,"size":1498791936,"categoryP":"porn","categoryS":"movies","magnet":"?xt=urn:btih:e0209ac76e70fbd06c027dfb4289dc6ffd360d51&amp;dn=Belle+e+Trapanate&amp;tr=udp%3A%2F%2Ftracker.openbittorrent.com%3A80&amp;tr=udp%3A%2F%2Fopen.demonii.com%3A1337&amp;tr=udp%3A%2F%2Ftracker.coppersurfer.tk%3A6969&amp;tr=udp%3A%2F%2Fexodus.desync.com%3A6969","seeders":0,"leechers":1,"uploader":"exmnova","files":1,"time":1290244853,"description":"Belle e Trapanate\n\n &lt;a href=&quot; http://www.picswan.com/img/share.php?id=B3FD_4CE78547&quot; rel=&quot;nofollow&quot; target=&quot;_NEW&quot;&gt; http://www.picswan.com/img/share.php?id=B3FD_4CE78547&lt;/a&gt;\n\n &lt;a href=&quot; http://www.picswan.com/img/share.php?id=C69B_4CE78547&quot; rel=&quot;nofollow&quot; target=&quot;_NEW&quot;&gt; http://www.picswan.com/img/share.php?id=C69B_4CE78547&lt;/a&gt;","torrent":{"xt":"urn:btih:e0209ac76e70fbd06c027dfb4289dc6ffd360d51","amp;dn":"Belle+e+Trapanate","amp;tr":["udp%3A%2F%2Ftracker.openbittorrent.com%3A80","udp%3A%2F%2Fopen.demonii.com%3A1337","udp%3A%2F%2Ftracker.coppersurfer.tk%3A6969","udp%3A%2F%2Fexodus.desync.com%3A6969"],"infoHash":"e0209ac76e70fbd06c027dfb4289dc6ffd360d51","infoHashBuffer":{"type":"Buffer","data":[224,32,154,199,110,112,251,208,108,2,125,251,66,137,220,111,253,54,13,81]},"announce":[],"urlList":[]}}