{"title":"Canon LBP 2900 Printer Driver","uid":6060093,"size":29478956,"categoryP":"applications","categoryS":"windows","magnet":"?xt=urn:btih:eb83e22d068e88040ae004281b565d2cbb277455&amp;dn=Canon+LBP+2900+Printer+Driver&amp;tr=udp%3A%2F%2Ftracker.openbittorrent.com%3A80&amp;tr=udp%3A%2F%2Fopen.demonii.com%3A1337&amp;tr=udp%3A%2F%2Ftracker.coppersurfer.tk%3A6969&amp;tr=udp%3A%2F%2Fexodus.desync.com%3A6969","seeders":0,"leechers":3,"uploader":"mamayr","files":200,"time":1293083772,"description":"CANON LBP 2900 PRINTER DRIVER FOR WINDOWS &lt;a href=&quot;\nhttp://img189.imageshack.us/img189/5421/sui8ii73xlsnhctfs.png&quot; rel=&quot;nofollow&quot; target=&quot;_NEW&quot;&gt;\nhttp://img189.imageshack.us/img189/5421/sui8ii73xlsnhctfs.png&lt;/a&gt; &lt;a href=&quot;\nhttp://img221.imageshack.us/img221/9062/screenshot1qn.jpg&quot; rel=&quot;nofollow&quot; target=&quot;_NEW&quot;&gt;\nhttp://img221.imageshack.us/img221/9062/screenshot1qn.jpg&lt;/a&gt;","torrent":{"xt":"urn:btih:eb83e22d068e88040ae004281b565d2cbb277455","amp;dn":"Canon+LBP+2900+Printer+Driver","amp;tr":["udp%3A%2F%2Ftracker.openbittorrent.com%3A80","udp%3A%2F%2Fopen.demonii.com%3A1337","udp%3A%2F%2Ftracker.coppersurfer.tk%3A6969","udp%3A%2F%2Fexodus.desync.com%3A6969"],"infoHash":"eb83e22d068e88040ae004281b565d2cbb277455","infoHashBuffer":{"type":"Buffer","data":[235,131,226,45,6,142,136,4,10,224,4,40,27,86,93,44,187,39,116,85]},"announce":[],"urlList":[]}}