{"title":"[720p] Ass Masterpiece - Franceska Jaimes ","uid":6111205,"size":1314987029,"categoryP":"porn","categoryS":"hd___movies","magnet":"?xt=urn:btih:eceb65246a6c91907f342860afd39cd12527fc63&amp;dn=%5B720p%5D+Ass+Masterpiece+-+Franceska+Jaimes+&amp;tr=udp%3A%2F%2Ftracker.openbittorrent.com%3A80&amp;tr=udp%3A%2F%2Fopen.demonii.com%3A1337&amp;tr=udp%3A%2F%2Ftracker.coppersurfer.tk%3A6969&amp;tr=udp%3A%2F%2Fexodus.desync.com%3A6969","seeders":0,"leechers":1,"uploader":"beta2008x","files":1,"time":1295358594,"description":" &lt;a href=&quot;http://www.dumppix.com/viewer.php?file=53ib8_Franceska_Jaimes_1.jpg&quot; rel=&quot;nofollow&quot; target=&quot;_NEW&quot;&gt;http://www.dumppix.com/viewer.php?file=53ib8_Franceska_Jaimes_1.jpg&lt;/a&gt;\n &lt;a href=&quot;\nhttp://www.dumppix.com/viewer.php?file=yqtmp_Franceska_Jaimes_2.jpg&quot; rel=&quot;nofollow&quot; target=&quot;_NEW&quot;&gt;\nhttp://www.dumppix.com/viewer.php?file=yqtmp_Franceska_Jaimes_2.jpg&lt;/a&gt;\n &lt;a href=&quot;\nhttp://www.dumppix.com/viewer.php?file=how81_Franceska_Jaimes_3.jpg&quot; rel=&quot;nofollow&quot; target=&quot;_NEW&quot;&gt;\nhttp://www.dumppix.com/viewer.php?file=how81_Franceska_Jaimes_3.jpg&lt;/a&gt;\n &lt;a href=&quot;\nhttp://www.dumppix.com/viewer.php?file=lbrkl_Franceska_Jaimes_4.jpg&quot; rel=&quot;nofollow&quot; target=&quot;_NEW&quot;&gt;\nhttp://www.dumppix.com/viewer.php?file=lbrkl_Franceska_Jaimes_4.jpg&lt;/a&gt;\n &lt;a href=&quot;\nhttp://www.dumppix.com/viewer.php?file=1akd_amfranceskajordan_2k.jpg&quot; rel=&quot;nofollow&quot; target=&quot;_NEW&quot;&gt;\nhttp://www.dumppix.com/viewer.php?file=1akd_amfranceskajordan_2k.jpg&lt;/a&gt;\n\nAss Masterpiece - Franceska Jaimes \n\nActors: Franceska Jaimes, Jordan Ash\n\nRelease Date: January 18, 2011\n\nFranceska is a smoking hot Latina from Colombia. She wants to show off her perfect ass and flawless body. She oils herself up and lets Jordan Ash take control of her and show her ass off to its full potential.\n\n\n","torrent":{"xt":"urn:btih:eceb65246a6c91907f342860afd39cd12527fc63","amp;dn":"%5B720p%5D+Ass+Masterpiece+-+Franceska+Jaimes+","amp;tr":["udp%3A%2F%2Ftracker.openbittorrent.com%3A80","udp%3A%2F%2Fopen.demonii.com%3A1337","udp%3A%2F%2Ftracker.coppersurfer.tk%3A6969","udp%3A%2F%2Fexodus.desync.com%3A6969"],"infoHash":"eceb65246a6c91907f342860afd39cd12527fc63","infoHashBuffer":{"type":"Buffer","data":[236,235,101,36,106,108,145,144,127,52,40,96,175,211,156,209,37,39,252,99]},"announce":[],"urlList":[]}}