{"title":"And Soon The Darkness (2010) BRRip 500MB","uid":6060849,"size":522807329,"categoryP":"video","categoryS":"movies","magnet":"?xt=urn:btih:f65482c66ea48f6ca038366a0be17041ec34a83e&amp;dn=And+Soon+The+Darkness+%282010%29+BRRip+500MB&amp;tr=udp%3A%2F%2Ftracker.openbittorrent.com%3A80&amp;tr=udp%3A%2F%2Fopen.demonii.com%3A1337&amp;tr=udp%3A%2F%2Ftracker.coppersurfer.tk%3A6969&amp;tr=udp%3A%2F%2Fexodus.desync.com%3A6969","seeders":0,"leechers":1,"uploader":"mcd23","files":1,"time":1293115378,"description":"When two American girls on a bike trip in a remote part of Argentina split up and one of them goes missing, the other must find her before her worst fears are realized.\n\n\n\n\n \n[FORMAT: Matroska\n[AWARDS: none as of now\n[GENRE: Horror | Thriller\n[FILE :SIZE 500 MiB\n[NO OF CDs: 1\n[RESOLUTION :1280*528\n[ASPECT RATIO[FRAME RATE]: 23.976 fps\n[LANGUAGE:  English\n[SUBTITLES: none\n[ORIGINAL: RUNTIME 01:31:00\n[RELEASE: RUNTIME 01:31:00\n[SOURCE: 720p-Japhson\n\n Tralier: &lt;a href=&quot;\nhttp://www.imdb.com/video/imdb/vi2266011929/&quot; rel=&quot;nofollow&quot; target=&quot;_NEW&quot;&gt;\nhttp://www.imdb.com/video/imdb/vi2266011929/&lt;/a&gt;\n\nscreen shots &lt;a href=&quot;\nhttp://img809.imageshack.us/i/andsoonthedarkness20107.png/&quot; rel=&quot;nofollow&quot; target=&quot;_NEW&quot;&gt;\nhttp://img809.imageshack.us/i/andsoonthedarkness20107.png/&lt;/a&gt; &lt;a href=&quot;\nhttp://img225.imageshack.us/i/andsoonthedarkness20107.png/&quot; rel=&quot;nofollow&quot; target=&quot;_NEW&quot;&gt;\nhttp://img225.imageshack.us/i/andsoonthedarkness20107.png/&lt;/a&gt;","torrent":{"xt":"urn:btih:f65482c66ea48f6ca038366a0be17041ec34a83e","amp;dn":"And+Soon+The+Darkness+%282010%29+BRRip+500MB","amp;tr":["udp%3A%2F%2Ftracker.openbittorrent.com%3A80","udp%3A%2F%2Fopen.demonii.com%3A1337","udp%3A%2F%2Ftracker.coppersurfer.tk%3A6969","udp%3A%2F%2Fexodus.desync.com%3A6969"],"infoHash":"f65482c66ea48f6ca038366a0be17041ec34a83e","infoHashBuffer":{"type":"Buffer","data":[246,84,130,198,110,164,143,108,160,56,54,106,11,225,112,65,236,52,168,62]},"announce":[],"urlList":[]}}