{"title":"[720p].FacialFest.-.Roxi","uid":5954362,"size":720314248,"categoryP":"porn","categoryS":"hd___movies","magnet":"?xt=urn:btih:f87d867711f78740baae29925f0805a22989f637&amp;dn=%5B720p%5D.FacialFest.-.Roxi&amp;tr=udp%3A%2F%2Ftracker.openbittorrent.com%3A80&amp;tr=udp%3A%2F%2Fopen.demonii.com%3A1337&amp;tr=udp%3A%2F%2Ftracker.coppersurfer.tk%3A6969&amp;tr=udp%3A%2F%2Fexodus.desync.com%3A6969","seeders":0,"leechers":1,"uploader":"exmnova","files":1,"time":1289654190,"description":"[720p][FacialFest.com / BangBros.com] Roxi (Every Thing`s Bigger In Texas..!!)\n\n &lt;a href=&quot;\nhttp://www.picswan.com/img/share.php?id=1282_4CDE8036&quot; rel=&quot;nofollow&quot; target=&quot;_NEW&quot;&gt;\nhttp://www.picswan.com/img/share.php?id=1282_4CDE8036&lt;/a&gt;\n\n\nMore Info:\n\n\n &lt;a href=&quot;\nhttp://www.69bits.com/torrent/HD/24918/%5B720p%5D.FacialFest.-.Roxi.html&quot; rel=&quot;nofollow&quot; target=&quot;_NEW&quot;&gt;\nhttp://www.69bits.com/torrent/HD/24918/%5B720p%5D.FacialFest.-.Roxi.html&lt;/a&gt;","torrent":{"xt":"urn:btih:f87d867711f78740baae29925f0805a22989f637","amp;dn":"%5B720p%5D.FacialFest.-.Roxi","amp;tr":["udp%3A%2F%2Ftracker.openbittorrent.com%3A80","udp%3A%2F%2Fopen.demonii.com%3A1337","udp%3A%2F%2Ftracker.coppersurfer.tk%3A6969","udp%3A%2F%2Fexodus.desync.com%3A6969"],"infoHash":"f87d867711f78740baae29925f0805a22989f637","infoHashBuffer":{"type":"Buffer","data":[248,125,134,119,17,247,135,64,186,174,41,146,95,8,5,162,41,137,246,55]},"announce":[],"urlList":[]}}